kandown/__init__.py
kandown/app.py
kandown/cli.py
kandown/models.py
kandown/py.typed
kandown/request_models.py
kandown/statics/api-cli.js
kandown/statics/api-filesystem.js
kandown/statics/api-local-storage.js
kandown/statics/api-page.js
kandown/statics/api-readonly.js
kandown/statics/api.js
kandown/statics/board.css
kandown/statics/board.js
kandown/statics/event-manager.js
kandown/statics/favicon.svg
kandown/statics/modal-manager.js
kandown/statics/mode.js
kandown/statics/settings.js
kandown/statics/types.js
kandown/statics/ui-utils.js
kandown/statics/ui.js
kandown/statics/visibility.css
kandown/storage.py
kandown/task_repo.py
kandown/templates/index.html
kandown-0.1.5.dist-info/WHEEL
kandown-0.1.5.dist-info/entry_points.txt
kandown-0.1.5.dist-info/METADATA
kandown-0.1.5.dist-info/RECORD
