Metadata-Version: 2.3
Name: kandown
Version: 0.1.5
Summary: Kandown is a lightweight, markdown-inspired Kanban board application that lets you manage tasks using a simple YAML file, featuring a web UI, image and markdown support, and a hybrid demo mode for browser-based or local file storage.
Keywords: kanban,markdown,task management,flask,yaml
Author: Maic Siemering
Author-email: Maic Siemering <maic@siemering.tech>
License: MIT
Classifier: Programming Language :: Python :: 3
Classifier: Programming Language :: Python :: 3.14
Classifier: Programming Language :: Python :: 3.13
Classifier: Programming Language :: Python :: 3.12
Classifier: Programming Language :: Python :: 3.11
Classifier: Programming Language :: Python :: 3.10
Classifier: License :: OSI Approved :: MIT License
Classifier: Operating System :: OS Independent
Classifier: Framework :: Flask
Classifier: Topic :: Software Development :: Libraries :: Application Frameworks
Classifier: Topic :: Utilities
Requires-Dist: flask>=3.1.2
Requires-Dist: markdown>=3.10
Requires-Dist: click>=8.3.0
Requires-Dist: pyyaml>=6.0.3
Requires-Dist: atomicwrites>=1.4.1
Requires-Dist: pydantic>=2.12.4
Requires-Dist: waitress>=3.0.2
Requires-Python: >=3.10
Project-URL: Backlog, https://eruvanos.github.io/kandown/?backlog=https://raw.githubusercontent.com/eruvanos/kandown/refs/heads/main/backlog.yaml
Project-URL: GitHub, https://github.com/eruvanos/kandown
Project-URL: Issues, https://github.com/eruvanos/kandown/issues
Project-URL: Live Page, https://eruvanos.github.io/kandown
